<annotation>
	<folder>raw</folder>
	<filename>nike21.jpg</filename>
	<path>C:\CV_DeepLearning\LOGOdetection\img_logo\raw\nike21.jpg</path>
	<source>
		<database>Unknown</database>
	</source>
	<size>
		<width>656</width>
		<height>688</height>
		<depth>3</depth>
	</size>
	<segmented>0</segmented>
	<object>
		<name>nike</name>
		<pose>Unspecified</pose>
		<truncated>0</truncated>
		<difficult>0</difficult>
		<bndbox>
			<xmin>197</xmin>
			<ymin>266</ymin>
			<xmax>500</xmax>
			<ymax>390</ymax>
		</bndbox>
	</object>
</annotation>
