<annotation>
	<folder>raw</folder>
	<filename>ss38.jpg</filename>
	<path>C:\CV_DeepLearning\LOGOdetection\img_logo\raw\ss38.jpg</path>
	<source>
		<database>Unknown</database>
	</source>
	<size>
		<width>356</width>
		<height>357</height>
		<depth>3</depth>
	</size>
	<segmented>0</segmented>
	<object>
		<name>samsung</name>
		<pose>Unspecified</pose>
		<truncated>0</truncated>
		<difficult>0</difficult>
		<bndbox>
			<xmin>122</xmin>
			<ymin>72</ymin>
			<xmax>292</xmax>
			<ymax>122</ymax>
		</bndbox>
	</object>
</annotation>
